neuber_correction/__init__.py
neuber_correction/neuber_correction.py
neuber_correction/performance_test.py
neuber_correction/test_neuber_correction.py
neuber_correction-0.1.19a0.dist-info/METADATA
neuber_correction-0.1.19a0.dist-info/WHEEL
neuber_correction-0.1.19a0.dist-info/licenses/LICENSE
neuber_correction-0.1.19a0.dist-info/RECORD
