Metadata-Version: 2.4
Name: neuber-correction
Version: 0.1.19a0
Summary: Neuber correction for fatigue life prediction
Author-email: Manuel Ramsaier <manuel.ramsaier89@gmail.com>
License-File: LICENSE
Classifier: Development Status :: 3 - Alpha
Classifier: License :: OSI Approved :: MIT License
Classifier: Operating System :: OS Independent
Classifier: Programming Language :: Python :: 3
Requires-Python: >=3.11
Requires-Dist: matplotlib>=3.10.3
Requires-Dist: numpy>=2.3.1
